{
  "generated_at": "2026-06-19T19:28:53.711102Z",
  "merge_strategy": "url_or_title_similarity_v0_6",
  "total_events": 44,
  "events": [
    {
      "story_id": "story_d9be48ef0825",
      "item_id": "47110deb7f3e162cc8901d23c0373ad57da4d3a1",
      "merged_into": "story_d9be48ef0825",
      "reason": "canonical_url",
      "similarity": 1.0
    },
    {
      "story_id": "story_ded9a2aae3f9",
      "item_id": "62ddfe6da2430cae0a24e0a61421f68f645987d8",
      "merged_into": "story_ded9a2aae3f9",
      "reason": "canonical_url",
      "similarity": 1.0
    },
    {
      "story_id": "story_d921c823d14e",
      "item_id": "f570809d19d190acd1fdb2acf9489740d4fa0d08",
      "merged_into": "story_d921c823d14e",
      "reason": "canonical_url",
      "similarity": 1.0
    },
    {
      "story_id": "story_cf240241f3d7",
      "item_id": "8b15b541dd9c3164c242725f457d4265efe2b88d",
      "merged_into": "story_cf240241f3d7",
      "reason": "canonical_url",
      "similarity": 1.0
    },
    {
      "story_id": "story_b90ea68d3583",
      "item_id": "c9ca8c76da533a8400149f7d57b91e17ef48e600",
      "merged_into": "story_b90ea68d3583",
      "reason": "title_similarity",
      "similarity": 1.0
    },
    {
      "story_id": "story_8d2f277efd93",
      "item_id": "dac92555236efcfb4dd2b027e8dc73bac0447ff5",
      "merged_into": "story_8d2f277efd93",
      "reason": "canonical_url",
      "similarity": 1.0
    },
    {
      "story_id": "story_8d2f277efd93",
      "item_id": "9b6421b74a99026eba9c8b589f4ba66792c87530",
      "merged_into": "story_8d2f277efd93",
      "reason": "canonical_url",
      "similarity": 1.0
    },
    {
      "story_id": "story_9bb7cc85fd74",
      "item_id": "29ad10934f28a80cdc8117aa37b90d2865e40563",
      "merged_into": "story_9bb7cc85fd74",
      "reason": "canonical_url",
      "similarity": 1.0
    },
    {
      "story_id": "story_42c2eb39116d",
      "item_id": "09cf5f59e090e95066695d82f7017c335690051d",
      "merged_into": "story_42c2eb39116d",
      "reason": "title_similarity",
      "similarity": 0.9613
    },
    {
      "story_id": "story_214879c336ff",
      "item_id": "0744f25be270212752b342642d6ab94d2eaa4973",
      "merged_into": "story_214879c336ff",
      "reason": "canonical_url",
      "similarity": 1.0
    },
    {
      "story_id": "story_99c8715080eb",
      "item_id": "9a6cbc0ffc279bb5cdae0105913cb947fe29d839",
      "merged_into": "story_99c8715080eb",
      "reason": "canonical_url",
      "similarity": 1.0
    },
    {
      "story_id": "story_c678e6510048",
      "item_id": "e7134f1f9568b4519eb27d9e100d2ac665fec4e6",
      "merged_into": "story_c678e6510048",
      "reason": "canonical_url",
      "similarity": 1.0
    },
    {
      "story_id": "story_b90ea68d3583",
      "item_id": "447370e82bfabc1713588e2dd8f1603973e4417a",
      "merged_into": "story_b90ea68d3583",
      "reason": "canonical_url",
      "similarity": 1.0
    },
    {
      "story_id": "story_e336da015ea3",
      "item_id": "b135edcd42555f48459beb543c35c39f2dbbf4b4",
      "merged_into": "story_e336da015ea3",
      "reason": "title_similarity",
      "similarity": 0.8621
    },
    {
      "story_id": "story_8208bc0e8979",
      "item_id": "57fe34673e1c0b67812b33e87b8d9cd13f9243e6",
      "merged_into": "story_8208bc0e8979",
      "reason": "canonical_url",
      "similarity": 1.0
    },
    {
      "story_id": "story_3ab16d83476b",
      "item_id": "0dc527835203edb2c253d7a0071c8418e95a2542",
      "merged_into": "story_3ab16d83476b",
      "reason": "canonical_url",
      "similarity": 1.0
    },
    {
      "story_id": "story_82afa1246b7b",
      "item_id": "0a99f35f7fadbd08609753a2466c72ccb8cd3e23",
      "merged_into": "story_82afa1246b7b",
      "reason": "canonical_url",
      "similarity": 1.0
    },
    {
      "story_id": "story_1f0870a4159b",
      "item_id": "6f6cff39e8eff246b108016c750917e0a50baa52",
      "merged_into": "story_1f0870a4159b",
      "reason": "canonical_url",
      "similarity": 1.0
    },
    {
      "story_id": "story_1e879cb61007",
      "item_id": "83b292c160eeb4aeac243457b8bb654a8300ce2d",
      "merged_into": "story_1e879cb61007",
      "reason": "canonical_url",
      "similarity": 1.0
    },
    {
      "story_id": "story_878aebdd4c70",
      "item_id": "3d0eb861693c73535708518944795183b8272867",
      "merged_into": "story_878aebdd4c70",
      "reason": "canonical_url",
      "similarity": 1.0
    },
    {
      "story_id": "story_3b2ac8f2e354",
      "item_id": "5048d8201d93cb12a2582922add24def1a71c3ff",
      "merged_into": "story_3b2ac8f2e354",
      "reason": "canonical_url",
      "similarity": 1.0
    },
    {
      "story_id": "story_c76594c12c3c",
      "item_id": "a2904a315896fd343eb7824a6d91fb1ba91abb2b",
      "merged_into": "story_c76594c12c3c",
      "reason": "canonical_url",
      "similarity": 1.0
    },
    {
      "story_id": "story_ebf58b228320",
      "item_id": "b47414843292a6e7aa1240640de86755477bc86b",
      "merged_into": "story_ebf58b228320",
      "reason": "canonical_url",
      "similarity": 1.0
    },
    {
      "story_id": "story_4762fe5e6329",
      "item_id": "0876a544925106d6aa893b344e8fddda0dbb9abd",
      "merged_into": "story_4762fe5e6329",
      "reason": "canonical_url",
      "similarity": 1.0
    },
    {
      "story_id": "story_41edf386fb58",
      "item_id": "16bfb2dff2e831876b77c1d5134a654f0bd6518f",
      "merged_into": "story_41edf386fb58",
      "reason": "canonical_url",
      "similarity": 1.0
    },
    {
      "story_id": "story_bcd29eb51485",
      "item_id": "5094a0f7dccdb205381b9e5c71f1c2d6b5ff6070",
      "merged_into": "story_bcd29eb51485",
      "reason": "canonical_url",
      "similarity": 1.0
    },
    {
      "story_id": "story_9bb7cc85fd74",
      "item_id": "169dc98c7e018e00e98297e94454cc115554cee1",
      "merged_into": "story_9bb7cc85fd74",
      "reason": "canonical_url",
      "similarity": 1.0
    },
    {
      "story_id": "story_4515a132b6d1",
      "item_id": "4d8355285831265fcbd5fbcdd5a51a8f3890cf05",
      "merged_into": "story_4515a132b6d1",
      "reason": "canonical_url",
      "similarity": 1.0
    },
    {
      "story_id": "story_b2c3f6155af5",
      "item_id": "8087c102389623eb89ad2ed4e7b6cd80ee601acb",
      "merged_into": "story_b2c3f6155af5",
      "reason": "title_similarity",
      "similarity": 0.8835
    },
    {
      "story_id": "story_7ac6691a7778",
      "item_id": "e8af757ba5eacb2b7dbab604ab4c7ba440375905",
      "merged_into": "story_7ac6691a7778",
      "reason": "canonical_url",
      "similarity": 1.0
    },
    {
      "story_id": "story_bcd29eb51485",
      "item_id": "f06cf4210940b96349940257bc79d0df9485e3cf",
      "merged_into": "story_bcd29eb51485",
      "reason": "canonical_url",
      "similarity": 1.0
    },
    {
      "story_id": "story_9bb7cc85fd74",
      "item_id": "862d6af95a4a9c0bf5fe53fbd347cadb0316e616",
      "merged_into": "story_9bb7cc85fd74",
      "reason": "canonical_url",
      "similarity": 1.0
    },
    {
      "story_id": "story_d102fb09e27f",
      "item_id": "6c2c876da2afd6580675888116029f7f3ba8d9df",
      "merged_into": "story_d102fb09e27f",
      "reason": "canonical_url",
      "similarity": 1.0
    },
    {
      "story_id": "story_2ccffc96e8e6",
      "item_id": "fac4b8d31c08898134ba4d951e462b5e7680379d",
      "merged_into": "story_2ccffc96e8e6",
      "reason": "canonical_url",
      "similarity": 1.0
    },
    {
      "story_id": "story_b7be7f52a78e",
      "item_id": "6362d36f472b2652699988767bcced92420f449e",
      "merged_into": "story_b7be7f52a78e",
      "reason": "canonical_url",
      "similarity": 1.0
    },
    {
      "story_id": "story_bac90ec5fb55",
      "item_id": "46053d92fe22770cc36ace2a2cf1e79f3f620930",
      "merged_into": "story_bac90ec5fb55",
      "reason": "canonical_url",
      "similarity": 1.0
    },
    {
      "story_id": "story_af27dced07f0",
      "item_id": "361f9dc089e9cf25f2ac212d5b60c6e719821605",
      "merged_into": "story_af27dced07f0",
      "reason": "canonical_url",
      "similarity": 1.0
    },
    {
      "story_id": "story_2df82173bb28",
      "item_id": "3a7b8e83166934f277c215b9d38c6ea9cc1c5a55",
      "merged_into": "story_2df82173bb28",
      "reason": "canonical_url",
      "similarity": 1.0
    },
    {
      "story_id": "story_2df82173bb28",
      "item_id": "511e0c5ba0fa0bcdb00aff975b1981f6f4e9b487",
      "merged_into": "story_2df82173bb28",
      "reason": "canonical_url",
      "similarity": 1.0
    },
    {
      "story_id": "story_2df82173bb28",
      "item_id": "873753a7dd7c986f82d7aaeaaf7c54080d2082f0",
      "merged_into": "story_2df82173bb28",
      "reason": "canonical_url",
      "similarity": 1.0
    },
    {
      "story_id": "story_1165e1d86c4a",
      "item_id": "37104e907778684fc6e859cbd5cd5331e81e8368",
      "merged_into": "story_1165e1d86c4a",
      "reason": "canonical_url",
      "similarity": 1.0
    },
    {
      "story_id": "story_58607cce10ee",
      "item_id": "0d585a19aae835564d8620ce54fd02356de92711",
      "merged_into": "story_58607cce10ee",
      "reason": "canonical_url",
      "similarity": 1.0
    },
    {
      "story_id": "story_d4e0bf6ebf73",
      "item_id": "2fca10fdc703d9fd900dd704ee885738e0757e99",
      "merged_into": "story_d4e0bf6ebf73",
      "reason": "canonical_url",
      "similarity": 1.0
    },
    {
      "story_id": "story_d6fe158cc16a",
      "item_id": "b32b8da8f156b35d7489a6379637e9d5410d2f88",
      "merged_into": "story_d6fe158cc16a",
      "reason": "title_similarity",
      "similarity": 1.0
    }
  ]
}